{
  "about": {
    "kicker": "Om oss",
    "title": "Om oss",
    "updated": "2026",
    "sections": [
      {
        "heading": "Om oss",
        "paragraphs": [
          "Raske mobilvennlige IQ- og akademiske quizer.",
          "Raske mobilvennlige IQ- og akademiske quizer."
        ]
      },
      {
        "heading": "Hva du far",
        "list": [
          "Raske mobilvennlige IQ- og akademiske quizer.",
          "100% gratis",
          "Poeng og rang"
        ]
      },
      {
        "heading": "Juridisk",
        "paragraphs": [
          "Raske mobilvennlige IQ- og akademiske quizer."
        ]
      }
    ]
  },
  "contact": {
    "kicker": "Kontakt",
    "title": "Kontakt",
    "updated": "2026",
    "sections": [
      {
        "heading": "Kontakt",
        "paragraphs": [
          "Raske mobilvennlige IQ- og akademiske quizer."
        ]
      },
      {
        "heading": "Personvernerklaering",
        "paragraphs": [
          "Raske mobilvennlige IQ- og akademiske quizer."
        ]
      },
      {
        "heading": "Quiz-ansvarsfraskrivelse",
        "paragraphs": [
          "Raske mobilvennlige IQ- og akademiske quizer."
        ]
      }
    ]
  },
  "accessibility": {
    "kicker": "Tilgjengelighet",
    "title": "Tilgjengelighet",
    "updated": "2026",
    "sections": [
      {
        "heading": "Tilgjengelighet",
        "paragraphs": [
          "Raske mobilvennlige IQ- og akademiske quizer."
        ]
      },
      {
        "heading": "Hva du far",
        "list": [
          "Start test",
          "Se resultater",
          "Start testen pa nytt"
        ]
      },
      {
        "heading": "Kontakt",
        "paragraphs": [
          "Raske mobilvennlige IQ- og akademiske quizer."
        ]
      }
    ]
  },
  "privacy-policy": {
    "kicker": "Juridisk",
    "title": "Personvernerklaering",
    "updated": "2026",
    "sections": [
      {
        "heading": "Personvernerklaering",
        "paragraphs": [
          "Raske mobilvennlige IQ- og akademiske quizer."
        ]
      },
      {
        "heading": "Cookiepolicy",
        "paragraphs": [
          "Se en kort annonse for a fortsette."
        ]
      },
      {
        "heading": "Kontakt",
        "paragraphs": [
          "Raske mobilvennlige IQ- og akademiske quizer."
        ]
      }
    ]
  },
  "cookie-policy": {
    "kicker": "Juridisk",
    "title": "Cookiepolicy",
    "updated": "2026",
    "sections": [
      {
        "heading": "Cookiepolicy",
        "paragraphs": [
          "Se en kort annonse for a fortsette."
        ]
      },
      {
        "heading": "Personvernerklaering",
        "paragraphs": [
          "Raske mobilvennlige IQ- og akademiske quizer."
        ]
      },
      {
        "heading": "Kontakt",
        "paragraphs": [
          "Raske mobilvennlige IQ- og akademiske quizer."
        ]
      }
    ]
  },
  "terms-of-use": {
    "kicker": "Juridisk",
    "title": "Bruksvilkar",
    "updated": "2026",
    "sections": [
      {
        "heading": "Bruksvilkar",
        "paragraphs": [
          "Raske mobilvennlige IQ- og akademiske quizer."
        ]
      },
      {
        "heading": "Quiz-ansvarsfraskrivelse",
        "paragraphs": [
          "Raske mobilvennlige IQ- og akademiske quizer."
        ]
      },
      {
        "heading": "Kontakt",
        "paragraphs": [
          "Raske mobilvennlige IQ- og akademiske quizer."
        ]
      }
    ]
  },
  "disclaimer": {
    "kicker": "Juridisk",
    "title": "Quiz-ansvarsfraskrivelse",
    "updated": "2026",
    "sections": [
      {
        "heading": "Quiz-ansvarsfraskrivelse",
        "paragraphs": [
          "Raske mobilvennlige IQ- og akademiske quizer."
        ]
      },
      {
        "heading": "Sluttpoeng",
        "paragraphs": [
          "Raske mobilvennlige IQ- og akademiske quizer."
        ]
      },
      {
        "heading": "Kontakt",
        "paragraphs": [
          "Raske mobilvennlige IQ- og akademiske quizer."
        ]
      }
    ]
  }
}
